convert_teams_wiki/__init__.py
convert_teams_wiki/__main__.py
convert_teams_wiki-0.1.2.dist-info/METADATA
convert_teams_wiki-0.1.2.dist-info/WHEEL
convert_teams_wiki-0.1.2.dist-info/licenses/LICENSE
convert_teams_wiki-0.1.2.dist-info/RECORD
