Metadata-Version: 2.3
Name: convert-teams-wiki
Version: 0.1.2
Summary: Convert a mht file for Microsoft Teams Wiki into markdown format
Project-URL: Homepage, https://github.com/kai2nenobu/convert-teams-wiki
Project-URL: Repository, https://github.com/kai2nenobu/convert-teams-wiki
Project-URL: Issues, https://github.com/kai2nenobu/convert-teams-wiki/issues
Project-URL: Changelog, https://github.com/kai2nenobu/convert-teams-wiki/blob/main/CHANGELOG.md
Author-email: Tsunenobu Kai <kai2nenobu@gmail.com>
License: MIT License
License-File: LICENSE
Keywords: markdown,teams,wiki
Classifier: Development Status :: 3 - Alpha
Classifier: Intended Audience :: Developers
Classifier: License :: OSI Approved :: MIT License
Classifier: Programming Language :: Python :: 3
Classifier: Programming Language :: Python :: 3.8
Classifier: Programming Language :: Python :: 3.9
Classifier: Programming Language :: Python :: 3.10
Classifier: Programming Language :: Python :: 3.11
Classifier: Programming Language :: Python :: 3.12
Requires-Python: >=3.8
Requires-Dist: beautifulsoup4>=4.5
